{
    "id": "1",
    "companyId": "1",
    "dateTime": "09/21/2021 3:33 PM",
    "name": "Fresh/Jr Back-end Dev (PHP/Python/Ruby)",
    "description": "We are looking for Back-end Engineer who are willing to learn about Ruby, passionate about coding,...",
    "salary": {
        "min": 500,
        "max": 800
    },
    "category": "fulltime",
    "address": {
        "province": "Da Nang",
        "detail": "Nam Ky Khoi Nghia, FPT City, Ngu Hanh Son, Da Nang"
    },
    "imagesAddress": {
        "imageAddress1": "storage/images/jobs/example1.png",
        "imageAddress2": "storage/images/jobs/example2.png",
        "imageAddress3": "storage/images/jobs/example3.png"
    },
    "apply" : [
        "1", "2"
    ]
}

